yext/__init__.py
yext/answers_universal_results.py
yext/exceptions.py
yext/yext_client.py
yext/etl/__init__.py
yext/etl/mapping.py
yext/etl/transform_profile.py
yext/etl/yext_etl.py
yext-0.6.8.dist-info/LICENSE
yext-0.6.8.dist-info/METADATA
yext-0.6.8.dist-info/WHEEL
yext-0.6.8.dist-info/top_level.txt
yext-0.6.8.dist-info/RECORD
