Metadata-Version: 2.1
Name: yext
Version: 0.6.8
Summary: Yext API Client for Python
Home-page: https://github.com/Yext/yext-client-python
Author: Yext Team
Author-email: mdavish@yext.com
Classifier: Programming Language :: Python :: 3
Classifier: License :: OSI Approved :: MIT License
Classifier: Operating System :: OS Independent
Requires-Python: >=3.7
License-File: LICENSE
